trumpet/__init__.py
trumpet/resources.py
trumpet/security.py
trumpet/util.py
trumpet/managers/__init__.py
trumpet/managers/base.py
trumpet/managers/admin/__init__.py
trumpet/templates/mainview.mako
trumpet/templates/mainview_bs4.mako
trumpet/views/__init__.py
trumpet/views/base.py
trumpet/views/client.py
trumpet/views/resourceviews.py
trumpet/views/static.py
trumpet/views/util.py
trumpet-0.2.11.dist-info/AUTHORS.rst
trumpet-0.2.11.dist-info/LICENSE
trumpet-0.2.11.dist-info/METADATA
trumpet-0.2.11.dist-info/WHEEL
trumpet-0.2.11.dist-info/entry_points.txt
trumpet-0.2.11.dist-info/top_level.txt
trumpet-0.2.11.dist-info/RECORD
