Metadata-Version: 2.1
Name: trumpet
Version: 0.2.11
Summary: Build a website with pyramid
Home-page: https://github.com/umeboshi2/trumpet
Author: Joseph Rawson
Author-email: joseph.rawson.works@gmail.com
License: UNLICENSED
Keywords: trumpet
Platform: UNKNOWN
Classifier: Development Status :: 2 - Pre-Alpha
Classifier: Intended Audience :: Developers
Classifier: License :: Public Domain
Classifier: Natural Language :: English
Classifier: Programming Language :: Python :: 3
Classifier: Programming Language :: Python :: 3.5
Requires-Dist: hornstone (>=0.1.21)
Requires-Dist: pyramid (>=1.9a)
Requires-Dist: pyramid-tm
Requires-Dist: plaster-pastedeploy
Requires-Dist: zope.sqlalchemy
Requires-Dist: pyramid-beaker
Requires-Dist: pyramid-mako
Requires-Dist: cornice
Requires-Dist: waitress
Requires-Dist: bcrypt
Requires-Dist: python-dateutil
Requires-Dist: querystring-parser
